{"sam":{"username":"sam","password":"12345","skill":"engineer","followers":["admin","wilson"],"status":{"likes":{}}},"admin":{"username":"admin","password":"12345","skill":"engineer","followers":["sam","wilson"],"status":{}},"wilson":{"username":"wilson","password":"12345","skill":"developer","followers":["admin","sam","samuel"],"status":{"status":"","likes":{"signedIn":"wilson"}}},"samuel":{"username":"samuel","password":"12345","skill":"engineer","followers":[],"status":{"status":"I don't want to be a product of my environment. I want my environment to be a product of me","likes":{"signedIn":"samuel"}}}}